numcube/__init__.py
numcube/axes.py
numcube/axis.py
numcube/cube.py
numcube/exceptions.py
numcube/functions.py
numcube/index.py
numcube/utils.py
numcube/version.py
numcube/experimental/__init__.py
numcube/experimental/multiaxis.py
numcube/experimental/multiindex.py
numcube/tests/__init__.py
numcube/tests/test_axis.py
numcube/tests/test_cube.py
numcube/tests/test_index.py
numcube/tests/test_multiaxis.py
numcube/tests/test_multiindex.py
numcube/tests/test_numcube.py
numcube/tests/doctests/__init__.py
numcube/tests/doctests/axis.py
numcube/tests/doctests/cube.py
numcube/tests/doctests/index.py
numcube-0.2.1.dist-info/LICENSE
numcube-0.2.1.dist-info/METADATA
numcube-0.2.1.dist-info/WHEEL
numcube-0.2.1.dist-info/top_level.txt
numcube-0.2.1.dist-info/RECORD
