Metadata-Version: 2.1
Name: numcube
Version: 0.2.1
Summary: Numcube extends the functionality of numpy multidimensional arrays by adding named and annotated axes.
Home-page: http://github.com/vladimir-kraus/numcube
Author: Vladimir Kraus
Author-email: vladimir.kraus@gmail.com
License: MIT
Keywords: cube,multidimensional,array,axis
Platform: UNKNOWN
Requires-Dist: numpy
